tigerflow/__init__.py
tigerflow/logconfig.py
tigerflow/models.py
tigerflow/pipeline.py
tigerflow/utils.py
tigerflow/cli/__init__.py
tigerflow/cli/report.py
tigerflow/cli/run.py
tigerflow/tasks/__init__.py
tigerflow/tasks/_base.py
tigerflow/tasks/local.py
tigerflow/tasks/local_async.py
tigerflow/tasks/slurm.py
tigerflow/tasks/utils.py
tigerflow-0.1.0a2.dist-info/METADATA
tigerflow-0.1.0a2.dist-info/WHEEL
tigerflow-0.1.0a2.dist-info/entry_points.txt
tigerflow-0.1.0a2.dist-info/licenses/LICENSE
tigerflow-0.1.0a2.dist-info/RECORD
