Metadata-Version: 2.4
Name: tigerflow
Version: 0.1.0a2
Summary: Data pipeline framework for Slurm-managed HPC clusters
Project-URL: Repository, https://github.com/princeton-ddss/tigerflow
Project-URL: Documentation, https://princeton-ddss.github.io/tigerflow/latest
Author-email: Sangyoon Park <datumvitae@gmail.com>
License-Expression: MIT
License-File: LICENSE
Requires-Python: >=3.10
Requires-Dist: aiofiles>=24.1.0
Requires-Dist: dask-jobqueue>=0.9.0
Requires-Dist: loguru>=0.7.3
Requires-Dist: networkx>=3.4.2
Requires-Dist: pydantic>=2.11.7
Requires-Dist: pyyaml>=6.0.2
Requires-Dist: typer>=0.16.0
Provides-Extra: examples
Requires-Dist: aiohttp>=3.12.15; extra == 'examples'
Requires-Dist: duckdb>=1.4.0; extra == 'examples'
Requires-Dist: openai-whisper>=20250625; extra == 'examples'
